scrybe/__main__.py
scrybe/filestate.py
scrybe/logger.py
scrybe/projectbuilder.py
scrybe/scriptbuilder.py
scrybe/translations.py
scrybe/utils.py
scrybe/scriptparser/__init__.py
scrybe/scriptparser/lexer.py
scrybe/scriptparser/parser.py
scrybe/scriptparser/parsetab.py
scrybe/setupparser/__init__.py
scrybe/setupparser/lexer.py
scrybe/setupparser/parser.py
scrybe/setupparser/parsetab.py
ScrybeLang-1.1.0.dist-info/LICENSE
ScrybeLang-1.1.0.dist-info/METADATA
ScrybeLang-1.1.0.dist-info/WHEEL
ScrybeLang-1.1.0.dist-info/entry_points.txt
ScrybeLang-1.1.0.dist-info/top_level.txt
ScrybeLang-1.1.0.dist-info/RECORD
