Metadata-Version: 2.1
Name: ScrybeLang
Version: 1.1.0
Summary: A text-based programming language that compiles to Scratch
Author-email: Bradley Pierce <bituvocoding@gmail.com>
License: GNU AFFERO GENERAL PUBLIC LICENSE
Project-URL: Homepage, https://github.com/ScrybeLang/Scrybe
Project-URL: Issues, https://github.com/ScrybeLang/Scrybe/issues
Keywords: scratch,compiler,text-based,python
Classifier: License :: OSI Approved :: GNU General Public License v3 (GPLv3)
Classifier: Environment :: Console
Classifier: Intended Audience :: Developers
Classifier: Topic :: Software Development :: Compilers
Classifier: Programming Language :: Python
Classifier: Programming Language :: Python :: 3
Classifier: Programming Language :: Python :: 3.12
Requires-Python: >=3.12
License-File: LICENSE
Requires-Dist: ScratchGen
Requires-Dist: ply
Requires-Dist: colorama
